pip_services4_rpc/__init__.py
pip_services4_rpc/clients/DirectClient.py
pip_services4_rpc/clients/__init__.py
pip_services4_rpc/commands/Command.py
pip_services4_rpc/commands/CommandSet.py
pip_services4_rpc/commands/Event.py
pip_services4_rpc/commands/ICommand.py
pip_services4_rpc/commands/ICommandInterceptor.py
pip_services4_rpc/commands/ICommandable.py
pip_services4_rpc/commands/IEvent.py
pip_services4_rpc/commands/IEventListener.py
pip_services4_rpc/commands/InterceptedCommand.py
pip_services4_rpc/commands/__init__.py
pip_services4_rpc/trace/InstrumentTiming.py
pip_services4_rpc/trace/__init__.py
pip_services4_rpc-0.0.1.dist-info/LICENSE
pip_services4_rpc-0.0.1.dist-info/METADATA
pip_services4_rpc-0.0.1.dist-info/WHEEL
pip_services4_rpc-0.0.1.dist-info/top_level.txt
pip_services4_rpc-0.0.1.dist-info/zip-safe
pip_services4_rpc-0.0.1.dist-info/RECORD
